criticalmaas/ta1_geopackage/__init__.py
criticalmaas/ta1_geopackage/core.py
criticalmaas/ta1_geopackage/fixtures/01-geopackage-structure.sql
criticalmaas/ta1_geopackage/fixtures/02-defs.sql
criticalmaas/ta1_geopackage/fixtures/03-tables.sql
criticalmaas/ta1_geopackage/procedures/insert-srid.sql
criticalmaas/ta1_geopackage/procedures/update-geometry-columns.sql
criticalmaas/ta1_geopackage/test_create_geopackage.py
criticalmaas/ta1_geopackage/test_geopandas.py
criticalmaas/ta1_geopackage/test_page_extractions.py
criticalmaas/ta1_geopackage/test_utils.py
criticalmaas_ta1_geopackage-0.2.1.dist-info/METADATA
criticalmaas_ta1_geopackage-0.2.1.dist-info/WHEEL
criticalmaas_ta1_geopackage-0.2.1.dist-info/RECORD
