Metadata-Version: 2.1
Name: criticalmaas.ta1-geopackage
Version: 0.2.1
Summary: GeoPackage schema for validating and storing vector geologic map data produced by computer-vision pipelines
License: MIT
Author: Daven Quinn
Author-email: code@davenquinn.com
Requires-Python: >=3.10,<4.0
Classifier: License :: OSI Approved :: MIT License
Classifier: Programming Language :: Python :: 3
Classifier: Programming Language :: Python :: 3.10
Classifier: Programming Language :: Python :: 3.11
Requires-Dist: fiona (>=1.9.5,<2.0.0)
Requires-Dist: geopandas (>=0.14.1,<0.15.0)
Requires-Dist: macrostrat-utils (>=1.2.0,<2.0.0)
Requires-Dist: macrostrat.database (>=3.1.2,<4.0.0)
Requires-Dist: pyogrio (>=0.7.2,<0.8.0)
